biom3d/__init__.py
biom3d/auto_config.py
biom3d/builder.py
biom3d/callbacks.py
biom3d/config_default.py
biom3d/eval.py
biom3d/gui.py
biom3d/logo_biom3d_minimal.png
biom3d/metrics.py
biom3d/omero_downloader.py
biom3d/omero_pred.py
biom3d/omero_preprocess_train.py
biom3d/omero_uploader.py
biom3d/pred.py
biom3d/predictors.py
biom3d/preprocess.py
biom3d/preprocess_train.py
biom3d/register.py
biom3d/train.py
biom3d/trainers.py
biom3d/datasets/__init__.py
biom3d/datasets/semseg_batchgen.py
biom3d/datasets/semseg_patch_fast.py
biom3d/datasets/semseg_torchio.py
biom3d/models/__init__.py
biom3d/models/decoder_vgg_deep.py
biom3d/models/encoder_efficientnet3d.py
biom3d/models/encoder_vgg.py
biom3d/models/unet3d_eff.py
biom3d/models/unet3d_vgg_deep.py
biom3d/utils/__init__.py
biom3d/utils/config.py
biom3d/utils/data_augmentation.py
biom3d/utils/decorators.py
biom3d/utils/deprecated.py
biom3d/utils/encoding.py
biom3d/utils/eval_metrics.py
biom3d/utils/filtering.py
biom3d/utils/fold.py
biom3d/utils/image.py
biom3d/utils/neural_network.py
biom3d/utils/os.py
biom3d/utils/time.py
biom3d/utils/data_handler/__init__.py
biom3d/utils/data_handler/data_handler_abstract.py
biom3d/utils/data_handler/data_handler_factory.py
biom3d/utils/data_handler/file_handler.py
biom3d/utils/data_handler/hdf5_handler.py
biom3d-0.1.2.dist-info/licenses/AUTHORS.md
biom3d-0.1.2.dist-info/licenses/LICENSE
biom3d-0.1.2.dist-info/METADATA
biom3d-0.1.2.dist-info/WHEEL
biom3d-0.1.2.dist-info/entry_points.txt
biom3d-0.1.2.dist-info/top_level.txt
biom3d-0.1.2.dist-info/RECORD
