Metadata-Version: 2.4
Name: biom3d
Version: 0.1.2
Summary: Biom3d. Framework for easy-to-use biomedical image segmentation.
Author-email: Guillaume Mougeot <guillaume.mougeot@laposte.net>
Project-URL: Homepage, https://github.com/GuillaumeMougeot/biom3d
Project-URL: Bug Tracker, https://github.com/GuillaumeMougeot/biom3d/issues
Keywords: deep learning,image segmentation,medical image analysis,medical image segmentation,biological image segmentation,bio-imaging
Classifier: Programming Language :: Python :: 3
Classifier: Operating System :: OS Independent
Requires-Python: >=3.9
License-File: LICENSE
License-File: AUTHORS.md
Requires-Dist: torch>=2.3
Requires-Dist: tqdm>=4.62.3
Requires-Dist: scikit-image>=0.14
Requires-Dist: scipy>=1.9.1
Requires-Dist: numpy>=1.21.2
Requires-Dist: SimpleITK>=2.1.1
Requires-Dist: pandas>=1.4.0
Requires-Dist: matplotlib>=3.5.3
Requires-Dist: tensorboard>=2.8.0
Requires-Dist: PyYAML>=5.4
Requires-Dist: torchio>=0.20.6
Requires-Dist: protobuf>=3.19.3
Requires-Dist: appdirs>=1.4.4
Requires-Dist: numba>=0.56.4
Requires-Dist: paramiko
Requires-Dist: netcat
Requires-Dist: tifffile
Requires-Dist: h5py
Requires-Dist: monai
Requires-Dist: einops
Provides-Extra: docs
Requires-Dist: sphinx>=4.1.2; extra == "docs"
Requires-Dist: sphinxcontrib-apidoc; extra == "docs"
Requires-Dist: sphinx_rtd_theme>=0.3.1; extra == "docs"
Requires-Dist: myst_nb; extra == "docs"
Requires-Dist: furo>=2022.06.21; extra == "docs"
Requires-Dist: docutils>=0.17.1; extra == "docs"
Requires-Dist: sphinx-copybutton; extra == "docs"
Requires-Dist: sphinx_design; extra == "docs"
Requires-Dist: sphinx_automodapi; extra == "docs"
Requires-Dist: pytorch_sphinx_theme; extra == "docs"
Provides-Extra: gui
Requires-Dist: omero-py; extra == "gui"
Requires-Dist: ezomero; extra == "gui"
Dynamic: license-file
